dragon/__init__.py
dragon/__main__.py
dragon/channels.cpython-311-x86_64-linux-gnu.so
dragon/dpmix.cpython-311-x86_64-linux-gnu.so
dragon/dtypes.cpython-311-x86_64-linux-gnu.so
dragon/fli.cpython-311-x86_64-linux-gnu.so
dragon/locks.cpython-311-x86_64-linux-gnu.so
dragon/managed_memory.cpython-311-x86_64-linux-gnu.so
dragon/perf.cpython-311-x86_64-linux-gnu.so
dragon/pheap.cpython-311-x86_64-linux-gnu.so
dragon/pmod.cpython-311-x86_64-linux-gnu.so
dragon/pydragon_channels.pyx
dragon/pydragon_dpmix.pyx
dragon/pydragon_dtypes.pyx
dragon/pydragon_fli.pyx
dragon/pydragon_heap.pyx
dragon/pydragon_lock.pyx
dragon/pydragon_managed_memory.pyx
dragon/pydragon_perf.pyx
dragon/pydragon_pmod.pyx
dragon/pydragon_rc.pyx
dragon/pydragon_utils.pyx
dragon/rc.cpython-311-x86_64-linux-gnu.so
dragon/utils.cpython-311-x86_64-linux-gnu.so
dragon/__pycache__/__init__.cpython-311.pyc
dragon/__pycache__/__main__.cpython-311.pyc
dragon/ai/__init__.py
dragon/ai/collective_group.py
dragon/ai/__pycache__/__init__.cpython-311.pyc
dragon/ai/__pycache__/collective_group.cpython-311.pyc
dragon/ai/torch/__init__.py
dragon/ai/torch/dataloader_monkeypatch.py
dragon/ai/torch/dictdataset.py
dragon/ai/torch/monkeypatching.py
dragon/ai/torch/__pycache__/__init__.cpython-311.pyc
dragon/ai/torch/__pycache__/dataloader_monkeypatch.cpython-311.pyc
dragon/ai/torch/__pycache__/dictdataset.cpython-311.pyc
dragon/ai/torch/__pycache__/monkeypatching.cpython-311.pyc
dragon/bin/dragon-cleanup
dragon/bin/dragon-hsta
dragon/bin/dragon-node-cleanup
dragon/cli/__init__.py
dragon/cli/__main__.py
dragon/cli/__pycache__/__init__.cpython-311.pyc
dragon/cli/__pycache__/__main__.cpython-311.pyc
dragon/data/__init__.py
dragon/data/__pycache__/__init__.cpython-311.pyc
dragon/data/ddict/__init__.py
dragon/data/ddict/ddict.py
dragon/data/ddict/manager.py
dragon/data/ddict/orchestrator.py
dragon/data/ddict/__pycache__/__init__.cpython-311.pyc
dragonhpc-0.13.dist-info/METADATA
dragonhpc-0.13.dist-info/WHEEL
dragonhpc-0.13.dist-info/entry_points.txt
dragonhpc-0.13.dist-info/top_level.txt
dragonhpc-0.13.dist-info/RECORD
