Metadata-Version: 2.4
Name: dragonhpc
Version: 0.13
Summary: Dragon is a composable distributed run-time for managing dynamic processes, memory, and data at scale through high-performance communication objects.
Author-email: Dragon Team <dragonhpc@hpe.com>
License: Dragon License:
Project-URL: Homepage, http://dragonhpc.org/portal/index.html
Project-URL: Documentation, https://dragonhpc.github.io/dragon/doc/_build/html/index.html
Project-URL: Repository, https://github.com/DragonHPC/dragon
Classifier: Programming Language :: Python :: 3
Classifier: License :: OSI Approved :: MIT License
Classifier: Operating System :: POSIX :: Linux
Requires-Python: >=3.10
Requires-Dist: cloudpickle>=3.0.0
Requires-Dist: gunicorn>=22.0.0
Requires-Dist: flask>=3.0.3
Requires-Dist: pyyaml>=6.0.2
Requires-Dist: requests>=2.32.2
Requires-Dist: psutil>=5.9.0
Requires-Dist: pycapnp<2.2.0,>=2.0.0
Requires-Dist: paramiko>=3.5.1
Requires-Dist: flask-jwt-extended>=4.7.1
Requires-Dist: networkx
Dynamic: requires-dist
Dynamic: requires-python
